mult_sec_4x4.vhd
library ieee;
use ieee.std_logic_1164.all;
use ieee.numeric_std.all;

entity mult_sec_4x4 is
  port (clk, st: in std_logic;
  mplier, mcand : in std_logic_vector(3 downto 0);
  done: out std_logic;
  product: out std_logic_vector (7 downto 0));
end mult_sec_4x4;

architecture comportamiento of mult_sec_4x4 is
  signal estado_act, estado_sig: integer range 0 to 9;
  signal acu_act, acu_sig: std_logic_vector(8 downto 0); -- accumulator
  signal Load, Ad, Sh: std_logic;
  signal suma: std_logic_vector(4 downto 0);
  -- alias acu_suma: std_logic_vector(3 downto 0) is acu_act(7 downto 4);
  -- alias m: std_logic is acu_act(0); -- m is bit 0 of acc
  signal acu_suma: std_logic_vector(3 downto 0);
  signal m: std_logic;
begin
  m <= acu_act(0);
  acu_suma <= acu_act(7 downto 4);


  product <= acu_act(7 downto 0);

  -- sumador
  suma <= std_logic_vector(('0' & unsigned(mcand)) + ('0' & unsigned(acu_suma)));

  -- memoria de estado y acumulador
  process (clk)
  begin
    if clk'event and clk = '1' then --  executes on rising edge of clock
      estado_act <= estado_sig;
      acu_act <= acu_sig;
    end if;
  end process;

  -- les controlador
  process (estado_act, st, m)
  begin
      -- Default values
      Load <= '0';
      Sh <= '0';
      Ad <= '0';
      Done <= '0';
      estado_sig <= estado_act;
      case estado_act is
        when 0 => --initial state
          if st = '1' then
            Load <= '1';
            estado_sig <= 1;
          end if;
        when 1 | 3 | 5 | 7 => -- "add/shift" state
          if m = '1' then -- add multiplicand to acc
            Ad <= '1';
            estado_sig <= estado_act + 1;
          else 
            Sh <= '1';
            estado_sig <= estado_act + 2;
          end if;
        when 2 | 4 | 6 | 8 => -- "shift" state
          Sh <= '1';
          estado_sig <= estado_act + 1;
        when 9 => -- end of cycle
          Done <= '1';
          estado_sig <= 0;
      end case;
  end process;

  -- les acumulador
  process (Load, Sh, Ad, mplier, acu_act, suma)
  begin
    if Load then 
      -- carga multiplicador en bits menos significativos
      -- borra bits restantes
      acu_sig <= "00000" & mplier;
    elsif Ad then
      -- carga la suma en los 5 bits mas significativos del acumulador
      acu_sig <= suma & acu_act(3 downto 0);
    elsif Sh then
      -- desplaza a derecha, completa MSB con cero
      acu_sig <= '0' & acu_act(8 downto 1);
    else 
      -- Si ninguna de las señales está activa, mantiene el contenido
      acu_sig <= acu_act;
    end if;
  end process;
end comportamiento;

tb_mult_sec_4x4.vhd
library ieee;
use ieee.std_logic_1164. all;
use ieee.numeric_std.all;
-- use ieee.std_logic_arith. all;
-- use ieee.std_logic_unsigned. all;
entity testmultsec is
  end testmultsec;
architecture test1 of testmultsec is
  component mult_sec_4x4
    port (clk: in std_logic;
          st: in std_logic;
    mplier, mcand: in std_logic_vector(3 downto 0);
    product: out std_logic_vector(7 downto 0);
    done: out std_logic);
  end component;
  constant N: integer:= 6;
  type arr is array(1 to N) of std_logic_vector(3 downto 0);
  constant MCANDARR: arr:= ("1101", "1011", "0001", "1000", "1111", "1101");
  constant MPLIERARR: arr:= ("1011", "1101", "0001", "1000", "1111","0000");
  signal clk: std_logic := '0';
  signal st, done1: std_logic;
  signal mplier, mcand: std_logic_vector(3 downto 0);
  signal product1: std_logic_vector(7 downto 0);
begin
  mult1: mult_sec_4x4 port map(clk, st, mplier, mcand, product1, done1);
  clk <= not clk after 10 ns; -- clock has 20 ns period
  process
  begin
    for i in 1 to n loop
      mcand <= MCANDARR(i);
      mplier <= MPLIERARR(i);
      st <= '1';
      wait until clk = '1' and clk'event;
      st <= '0';
      wait until (done1 = '1') ;
      wait until clk = '1' and clk'event;
    end loop;
    std.env.stop;
  end process;
end test1;

testbench.vcd
$date
  Thu Nov 16 16:53:33 2023
$end
$version
  GHDL v0
$end
$timescale
  1 fs
$end
$scope module standard $end
$upscope $end
$scope module textio $end
$upscope $end
$scope module std_logic_1164 $end
$upscope $end
$scope module numeric_std $end
$upscope $end
$scope module env $end
$upscope $end
$scope module testmultsec $end
$var reg 1 ! clk $end
$var reg 1 " st $end
$var reg 1 # done1 $end
$var reg 4 $ mplier[3:0] $end
$var reg 4 % mcand[3:0] $end
$var reg 8 & product1[7:0] $end
$scope module mult1 $end
$var reg 1 ' clk $end
$var reg 1 ( st $end
$var reg 4 ) mplier[3:0] $end
$var reg 4 * mcand[3:0] $end
$var reg 1 + done $end
$var reg 8 , product[7:0] $end
$var integer 32 - estado_act $end
$var integer 32 . estado_sig $end
$var reg 9 / acu_act[8:0] $end
$var reg 9 0 acu_sig[8:0] $end
$var reg 1 1 load $end
$var reg 1 2 ad $end
$var reg 1 3 sh $end
$var reg 5 4 suma[4:0] $end
$var reg 4 5 acu_suma[3:0] $end
$var reg 1 6 m $end
$upscope $end
$upscope $end
$enddefinitions $end
#0
0!
1"
0#
b1011 $
b1101 %
bUUUUUUUU &
0'
1(
b1011 )
b1101 *
0+
bUUUUUUUU ,
b0 -
b1 .
bUUUUUUUUU /
b000001011 0
11
02
03
bXXXXX 4
bUUUU 5
U6
#10000000
1!
0"
b00001011 &
1'
0(
b00001011 ,
b1 -
b10 .
b000001011 /
b011011011 0
01
12
03
b01101 4
b0000 5
16
#20000000
0!
0'
#30000000
1!
b11011011 &
1'
b11011011 ,
b10 -
b11 .
b011011011 /
b001101101 0
02
13
b11010 4
b1101 5
#40000000
0!
0'
#50000000
1!
b01101101 &
1'
b01101101 ,
b11 -
b100 .
b001101101 /
b100111101 0
12
03
b10011 4
b0110 5
#60000000
0!
0'
#70000000
1!
b00111101 &
1'
b00111101 ,
b100 -
b101 .
b100111101 /
b010011110 0
02
13
b10000 4
b0011 5
#80000000
0!
0'
#90000000
1!
b10011110 &
1'
b10011110 ,
b101 -
b111 .
b010011110 /
b001001111 0
02
13
b10110 4
b1001 5
06
#100000000
0!
0'
#110000000
1!
b01001111 &
1'
b01001111 ,
b111 -
b1000 .
b001001111 /
b100011111 0
12
03
b10001 4
b0100 5
16
#120000000
0!
0'
#130000000
1!
b00011111 &
1'
b00011111 ,
b1000 -
b1001 .
b100011111 /
b010001111 0
02
13
b01110 4
b0001 5
#140000000
0!
0'
#150000000
1!
1#
b10001111 &
1'
1+
b10001111 ,
b1001 -
b0 .
b010001111 /
b010001111 0
03
b10101 4
b1000 5
#160000000
0!
0'
#170000000
1!
1"
0#
b1101 $
b1011 %
1'
1(
b1101 )
b1011 *
0+
b0 -
b1 .
b000001101 0
11
b10011 4
#180000000
0!
0'
#190000000
1!
0"
b00001101 &
1'
0(
b00001101 ,
b1 -
b10 .
b000001101 /
b010111101 0
01
12
b01011 4
b0000 5
#200000000
0!
0'
#210000000
1!
b10111101 &
1'
b10111101 ,
b10 -
b11 .
b010111101 /
b001011110 0
02
13
b10110 4
b1011 5
#220000000
0!
0'
#230000000
1!
b01011110 &
1'
b01011110 ,
b11 -
b101 .
b001011110 /
b000101111 0
02
13
b10000 4
b0101 5
06
#240000000
0!
0'
#250000000
1!
b00101111 &
1'
b00101111 ,
b101 -
b110 .
b000101111 /
b011011111 0
12
03
b01101 4
b0010 5
16
#260000000
0!
0'
#270000000
1!
b11011111 &
1'
b11011111 ,
b110 -
b111 .
b011011111 /
b001101111 0
02
13
b11000 4
b1101 5
#280000000
0!
0'
#290000000
1!
b01101111 &
1'
b01101111 ,
b111 -
b1000 .
b001101111 /
b100011111 0
12
03
b10001 4
b0110 5
#300000000
0!
0'
#310000000
1!
b00011111 &
1'
b00011111 ,
b1000 -
b1001 .
b100011111 /
b010001111 0
02
13
b01100 4
b0001 5
#320000000
0!
0'
#330000000
1!
1#
b10001111 &
1'
1+
b10001111 ,
b1001 -
b0 .
b010001111 /
b010001111 0
03
b10011 4
b1000 5
#340000000
0!
0'
#350000000
1!
1"
0#
b0001 $
b0001 %
1'
1(
b0001 )
b0001 *
0+
b0 -
b1 .
b000000001 0
11
b01001 4
#360000000
0!
0'
#370000000
1!
0"
b00000001 &
1'
0(
b00000001 ,
b1 -
b10 .
b000000001 /
b000010001 0
01
12
b00001 4
b0000 5
#380000000
0!
0'
#390000000
1!
b00010001 &
1'
b00010001 ,
b10 -
b11 .
b000010001 /
b000001000 0
02
13
b00010 4
b0001 5
#400000000
0!
0'
#410000000
1!
b00001000 &
1'
b00001000 ,
b11 -
b101 .
b000001000 /
b000000100 0
02
13
b00001 4
b0000 5
06
#420000000
0!
0'
#430000000
1!
b00000100 &
1'
b00000100 ,
b101 -
b111 .
b000000100 /
b000000010 0
#440000000
0!
0'
#450000000
1!
b00000010 &
1'
b00000010 ,
b111 -
b1001 .
b000000010 /
b000000001 0
#460000000
0!
0'
#470000000
1!
1#
b00000001 &
1'
1+
b00000001 ,
b1001 -
b0 .
b000000001 /
b000000001 0
03
16
#480000000
0!
0'
#490000000
1!
1"
0#
b1000 $
b1000 %
1'
1(
b1000 )
b1000 *
0+
b0 -
b1 .
b000001000 0
11
b01000 4
#500000000
0!
0'
#510000000
1!
0"
b00001000 &
1'
0(
b00001000 ,
b1 -
b11 .
b000001000 /
b000000100 0
01
02
13
06
#520000000
0!
0'
#530000000
1!
b00000100 &
1'
b00000100 ,
b11 -
b101 .
b000000100 /
b000000010 0
#540000000
0!
0'
#550000000
1!
b00000010 &
1'
b00000010 ,
b101 -
b111 .
b000000010 /
b000000001 0
#560000000
0!
0'
#570000000
1!
b00000001 &
1'
b00000001 ,
b111 -
b1000 .
b000000001 /
b010000001 0
12
03
16
#580000000
0!
0'
#590000000
1!
b10000001 &
1'
b10000001 ,
b1000 -
b1001 .
b010000001 /
b001000000 0
02
13
b10000 4
b1000 5
#600000000
0!
0'
#610000000
1!
1#
b01000000 &
1'
1+
b01000000 ,
b1001 -
b0 .
b001000000 /
b001000000 0
03
b01100 4
b0100 5
06
#620000000
0!
0'
#630000000
1!
1"
0#
b1111 $
b1111 %
1'
1(
b1111 )
b1111 *
0+
b0 -
b1 .
b000001111 0
11
b10011 4
#640000000
0!
0'
#650000000
1!
0"
b00001111 &
1'
0(
b00001111 ,
b1 -
b10 .
b000001111 /
b011111111 0
01
12
03
b01111 4
b0000 5
16
#660000000
0!
0'
#670000000
1!
b11111111 &
1'
b11111111 ,
b10 -
b11 .
b011111111 /
b001111111 0
02
13
b11110 4
b1111 5
#680000000
0!
0'
#690000000
1!
b01111111 &
1'
b01111111 ,
b11 -
b100 .
b001111111 /
b101101111 0
12
03
b10110 4
b0111 5
#700000000
0!
0'
#710000000
1!
b01101111 &
1'
b01101111 ,
b100 -
b101 .
b101101111 /
b010110111 0
02
13
b10101 4
b0110 5
#720000000
0!
0'
#730000000
1!
b10110111 &
1'
b10110111 ,
b101 -
b110 .
b010110111 /
b110100111 0
12
03
b11010 4
b1011 5
#740000000
0!
0'
#750000000
1!
b10100111 &
1'
b10100111 ,
b110 -
b111 .
b110100111 /
b011010011 0
02
13
b11001 4
b1010 5
#760000000
0!
0'
#770000000
1!
b11010011 &
1'
b11010011 ,
b111 -
b1000 .
b011010011 /
b111000011 0
12
03
b11100 4
b1101 5
#780000000
0!
0'
#790000000
1!
b11000011 &
1'
b11000011 ,
b1000 -
b1001 .
b111000011 /
b011100001 0
02
13
b11011 4
b1100 5
#800000000
0!
0'
#810000000
1!
1#
b11100001 &
1'
1+
b11100001 ,
b1001 -
b0 .
b011100001 /
b011100001 0
03
b11101 4
b1110 5
#820000000
0!
0'
#830000000
1!
1"
0#
b0000 $
b1101 %
1'
1(
b0000 )
b1101 *
0+
b0 -
b1 .
b000000000 0
11
b11011 4
#840000000
0!
0'
#850000000
1!
0"
b00000000 &
1'
0(
b00000000 ,
b1 -
b11 .
b000000000 /
b000000000 0
01
02
13
b01101 4
b0000 5
06
#860000000
0!
0'
#870000000
1!
1'
b11 -
b101 .
#880000000
0!
0'
#890000000
1!
1'
b101 -
b111 .
#900000000
0!
0'
#910000000
1!
1'
b111 -
b1001 .
#920000000
0!
0'
#930000000
1!
1#
1'
1+
b1001 -
b0 .
03
